glowing_waffles/__init__.py
glowing_waffles/_astropy_init.py
glowing_waffles/conftest.py
glowing_waffles/coordinates.py
glowing_waffles/core.py
glowing_waffles/photometry.py
glowing_waffles/photutils_aperture_photometry.py
glowing_waffles/source_detection.py
glowing_waffles/version.py
glowing_waffles/data/Measurements-2015-08-03.csv
glowing_waffles/data/README.rst
glowing_waffles/data/all_kelt_1_measurements.csv
glowing_waffles/differential_photometry/__init__.py
glowing_waffles/differential_photometry/catalog_search.py
glowing_waffles/differential_photometry/magnitude_transforms.py
glowing_waffles/differential_photometry/vsx_mags.py
glowing_waffles/differential_photometry/tests/__init__.py
glowing_waffles/differential_photometry/tests/image-viewer.py
glowing_waffles/differential_photometry/tests/test_catalog_search.py
glowing_waffles/differential_photometry/tests/test_magnitude_transforms.py
glowing_waffles/differential_photometry/tests/test_vsx_mags.py
glowing_waffles/differential_photometry/tests/data/2014-12-29-ey-uma-9.fits
glowing_waffles/differential_photometry/tests/data/all_apass_ey_uma_sorted_ra_first_20.fits
glowing_waffles/differential_photometry/tests/data/clipped_ey_uma_vsx.fits
glowing_waffles/differential_photometry/tests/data/comp_stars.fits
glowing_waffles/differential_photometry/tests/data/low_error_apass_ey_uma_sorted_ra_first_20.fits
glowing_waffles/differential_photometry/tests/data/mag_transform.csv
glowing_waffles/differential_photometry/tests/data/sample_wcs_ey_uma.fits
glowing_waffles/differential_photometry/tests/data/unclipped_ey_uma_vsx.fits
glowing_waffles/differential_photometry/tests/data/variables.fits
glowing_waffles/io/__init__.py
glowing_waffles/io/aij.py
glowing_waffles/io/tests/__init__.py
glowing_waffles/io/tests/test_aij.py
glowing_waffles/tests/__init__.py
glowing_waffles/tests/coveragerc
glowing_waffles/tests/make_wcs.py
glowing_waffles/tests/setup_package.py
glowing_waffles/tests/test_coordinates.py
glowing_waffles-0.0.18.dist-info/METADATA
glowing_waffles-0.0.18.dist-info/WHEEL
glowing_waffles-0.0.18.dist-info/top_level.txt
glowing_waffles-0.0.18.dist-info/RECORD
